README.md
setup.py
lbrlabs_pulumi_grafana/__init__.py
lbrlabs_pulumi_grafana/_inputs.py
lbrlabs_pulumi_grafana/_utilities.py
lbrlabs_pulumi_grafana/alert_notification.py
lbrlabs_pulumi_grafana/annotation.py
lbrlabs_pulumi_grafana/api_key.py
lbrlabs_pulumi_grafana/builtin_role_assignment.py
lbrlabs_pulumi_grafana/cloud_access_policy.py
lbrlabs_pulumi_grafana/cloud_access_policy_token.py
lbrlabs_pulumi_grafana/cloud_api_key.py
lbrlabs_pulumi_grafana/cloud_plugin_installation.py
lbrlabs_pulumi_grafana/cloud_stack.py
lbrlabs_pulumi_grafana/cloud_stack_api_key.py
lbrlabs_pulumi_grafana/cloud_stack_service_account.py
lbrlabs_pulumi_grafana/cloud_stack_service_account_token.py
lbrlabs_pulumi_grafana/contact_point.py
lbrlabs_pulumi_grafana/dashboard.py
lbrlabs_pulumi_grafana/dashboard_permission.py
lbrlabs_pulumi_grafana/data_source.py
lbrlabs_pulumi_grafana/data_source_permission.py
lbrlabs_pulumi_grafana/folder.py
lbrlabs_pulumi_grafana/folder_permission.py
lbrlabs_pulumi_grafana/get_cloud_ips.py
lbrlabs_pulumi_grafana/get_cloud_organization.py
lbrlabs_pulumi_grafana/get_cloud_stack.py
lbrlabs_pulumi_grafana/get_dashboard.py
lbrlabs_pulumi_grafana/get_dashboards.py
lbrlabs_pulumi_grafana/get_data_source.py
lbrlabs_pulumi_grafana/get_folder.py
lbrlabs_pulumi_grafana/get_folders.py
lbrlabs_pulumi_grafana/get_grafan_slos.py
lbrlabs_pulumi_grafana/get_library_panel.py
lbrlabs_pulumi_grafana/get_on_call_slack_channel.py
lbrlabs_pulumi_grafana/get_oncall_action.py
lbrlabs_pulumi_grafana/get_oncall_escalation_chain.py
lbrlabs_pulumi_grafana/get_oncall_outgoing_webhook.py
lbrlabs_pulumi_grafana/get_oncall_schedule.py
lbrlabs_pulumi_grafana/get_oncall_team.py
lbrlabs_pulumi_grafana/get_oncall_user.py
lbrlabs_pulumi_grafana/get_oncall_user_group.py
lbrlabs_pulumi_grafana/get_organization.py
lbrlabs_pulumi_grafana/get_organization_preferences.py
lbrlabs_pulumi_grafana/get_role.py
lbrlabs_pulumi_grafana/get_slos.py
lbrlabs_pulumi_grafana/get_synthetic_monitoring_probe.py
lbrlabs_pulumi_grafana.egg-info/PKG-INFO
lbrlabs_pulumi_grafana.egg-info/SOURCES.txt
lbrlabs_pulumi_grafana.egg-info/dependency_links.txt
lbrlabs_pulumi_grafana.egg-info/not-zip-safe
lbrlabs_pulumi_grafana.egg-info/requires.txt
lbrlabs_pulumi_grafana.egg-info/top_level.txt
