Metadata-Version: 2.1
Name: lbrlabs-pulumi-grafana
Version: 0.0.12a1694442191
Summary: A Pulumi package for creating and managing grafana.
Home-page: https://www.pulumi.com
License: Apache-2.0
Project-URL: Repository, https://github.com/lbrlabs/pulumi-grafana
Keywords: pulumi grafana lbrlabs
Platform: UNKNOWN
Requires-Python: >=3.7
